{
  "TxAlreadyExists": "Transaction already exists on blockchain",
  "TxNotFound": "Transaction {{tx_hash}} not found",
  "TxInvalidNonce": "Transaction nonce {{tx_nonce}} must be larger than nonce of the used access key {{ak_nonce}}",
  "TxInvalidChain": "Transaction doesn't belong to the current chain",
  "InvalidReceiver": "Invalid receiver {{receiver_id}} according to requirements",
  "Timeout": "Timeout exceeded",
  "Closed": "Connection closed",
  "UnknownServerError": "Unknown server error: {{msg_text}}"
}
